EXTERNALS.txt
setup.cfg
setup.py
SimpleAuth_client.egg-info/PKG-INFO
SimpleAuth_client.egg-info/SOURCES.txt
SimpleAuth_client.egg-info/dependency_links.txt
SimpleAuth_client.egg-info/entry_points.txt
SimpleAuth_client.egg-info/requires.txt
SimpleAuth_client.egg-info/top_level.txt
SimpleAuth_client.egg-info/zip-safe
ez_setup/__init__.py
simple_auth/__init__.py
simple_auth/client/__init__.py
simple_auth/client/model.py
simple_auth/client/mysql_tables.py
simple_auth/client/oracle_tables.py
simple_auth/client/remote.py
simple_auth/client/config/__init__.py
simple_auth/client/config/classbuilder.py
simple_auth/client/docs/__init__.py
simple_auth/client/docs/basic_auth.txt
simple_auth/client/tests/__init__.py
simple_auth/client/tests/test_basic_auth.py
