Metadata-Version: 1.0
Name: SimpleAuth-client
Version: 0.4dev-r11
Summary: client for the SimpleAuth application
Home-page: http://www.simpleauth.com
Author: James Taylor
Author-email: baldtrol@gmail.com
License: MIT
Download-URL: http://simpleauth.googlecode.com/svn/projects/simpleauth_client/trunk
Keywords: simpleauth
Platform: UNKNOWN
